L2P.v
module L2P(
    input clk,
    input BUTTON,
    output L2P_out
);
reg L2P_out;
output reg BUTTON_tmp;

always @(posedge clk ) begin
    BUTTON_tmp<=BUTTON;
end

always @(posedge clk ) begin
    L2P_out<=(BUTTON_tmp^BUTTON)&!BUTTON_tmp;
end
endmodule

mimasuo_logic.v
module mimasuo_logic(
    input clk,
    input button0,
    input button1,
    input rst_n,
    output wire UNLOCK
);
wire zero;
wire one;
//reg state1,state0;
reg [3:0] state_n,state_c;
parameter s_00=4'b0001;
parameter s_01=4'b0010;
parameter s_10=4'b0100;
parameter s_11=4'b1000;

always @(posedge clk ) begin
    if(!rst_n) begin
        state_c<=s_00;
        state_n<=s_00;
    end
    else
        state_c<=state_n;
end

assign UNLOCK=(state_c==s_10)?1'b1:1'b0;

always @(*) begin
    case(state_c)
        s_00:begin
            if({one,zero}==2'b00) state_n<=s_00;
            else if({one,zero}==2'b10) state_n<=s_00;
            else if({one,zero}==2'b01) state_n<=s_11;
            else if({one,zero}==2'b11) state_n<=s_11;
        end
        s_01:begin
            if({one,zero}==2'b00) state_n<=s_01;
            else if({one,zero}==2'b10) state_n<=s_00;
            else if({one,zero}==2'b01) state_n<=s_10;
            else if({one,zero}==2'b11) state_n<=s_10;
        end
        s_10:begin
            if({one,zero}==2'b00) state_n<=s_10;
            else if({one,zero}==2'b10) state_n<=s_01;
            else if({one,zero}==2'b01) state_n<=s_11;
            else if({one,zero}==2'b11) state_n<=s_11;
        end
        s_11:begin
            if({one,zero}==2'b00) state_n<=s_11;
            else if({one,zero}==2'b10) state_n<=s_01;
            else if({one,zero}==2'b01) state_n<=s_11;
            else if({one,zero}==2'b11) state_n<=s_11;
        end
        default: state_n <= state_c;
    endcase
end
L2P L2P_button0(
    .clk(clk),
    .BUTTON(button0),
    .L2P_out(zero)
);
L2P L2P_button1(
    .clk(clk),
    .BUTTON(button1),
    .L2P_out(one)
);

endmodule

mimasuo_logic_tb.v
`timescale 1 ns / 10 ps
module mimasuo_logic_tb();
    reg clk;
    reg button0;
    reg button1;
    reg rst_n;
    
    wire UNLOCK;
    initial begin
        $dumpfile("mimasuo_logic.vcd");
        $dumpvars(0,mimasuo_logic_tb);
    end
    always begin
        #10
        clk=~clk;
    end
    initial begin
        clk=0;
        button0=0;
        button1=0;
        rst_n=0;
        #20
        rst_n=1;
        button0=0;
        button1=0;
        #20
        button0=1;
        button1=0;
        #20
        button0=0;
        button1=0;
        #20
        button0=0;
        button1=1;
        #20
        button0=0;
        button1=0;
        #20
        button0=1;
        button1=0;
        #20
        button0=0;
        button1=0;
        #20
        button0=1;
        button1=0;
        #20
        button0=0;
        button1=1;
        #20
        $finish;
    end
    mimasuo_logic u_mimasuo_logic(
        .clk(clk),
        .rst_n(rst_n),
        .button0(button0),
        .button1(button1),
        .UNLOCK(UNLOCK)
    );
endmodule

mimasuo_logic.vcd
$date
	Thu Nov 16 10:06:27 2023
$end
$version
	Icarus Verilog
$end
$timescale
	10ps
$end
$scope module mimasuo_logic_tb $end
$var wire 1 ! UNLOCK $end
$var reg 1 " button0 $end
$var reg 1 # button1 $end
$var reg 1 $ clk $end
$var reg 1 % rst_n $end
$scope module u_mimasuo_logic $end
$var wire 1 " button0 $end
$var wire 1 # button1 $end
$var wire 1 $ clk $end
$var wire 1 % rst_n $end
$var wire 1 & zero $end
$var wire 1 ' one $end
$var wire 1 ! UNLOCK $end
$var parameter 4 ( s_00 $end
$var parameter 4 ) s_01 $end
$var parameter 4 * s_10 $end
$var parameter 4 + s_11 $end
$var reg 4 , state_c [3:0] $end
$var reg 4 - state_n [3:0] $end
$scope module L2P_button0 $end
$var wire 1 " BUTTON $end
$var wire 1 $ clk $end
$var reg 1 . BUTTON_tmp $end
$var reg 1 & L2P_out $end
$upscope $end
$scope module L2P_button1 $end
$var wire 1 # BUTTON $end
$var wire 1 $ clk $end
$var reg 1 / BUTTON_tmp $end
$var reg 1 ' L2P_out $end
$upscope $end
$upscope $end
$upscope $end
$enddefinitions $end
$comment Show the parameter values. $end
$dumpall
b1000 +
b100 *
b10 )
b1 (
$end
#0
$dumpvars
x/
x.
bx -
bx ,
x'
x&
0%
0$
0#
0"
x!
$end
#1000
0!
0.
0/
b1 -
b1 ,
1$
#2000
0$
1%
#3000
0'
0&
1$
#4000
0$
1"
#5000
b1000 -
1.
1&
1$
#6000
0$
0"
#7000
b1000 ,
0&
0.
1$
#8000
0$
1#
#9000
b10 -
1/
1'
1$
#10000
0$
0#
#11000
b10 ,
0'
0/
1$
#12000
0$
1"
#13000
b100 -
1.
1&
1$
#14000
0$
0"
#15000
1!
b100 ,
0&
0.
1$
#16000
0$
1"
#17000
b1000 -
1.
1&
1$
#18000
0$
1#
0"
#19000
b10 -
0!
b1000 ,
1'
1/
0&
0.
1$
